mson/__init__.py
mson/dumping.py
mson/parsing.py
mson-0.1.0.dist-info/WHEEL
mson-0.1.0.dist-info/METADATA
mson-0.1.0.dist-info/RECORD
