Metadata-Version: 2.1
Name: mson
Version: 0.1.0
Summary: MSON serializer/de-serializer
License: WTFPL
Author: Rémy Sanchez
Author-email: remy.sanchez@hyperthese.net
Requires-Python: >=3.8,<4.0
Classifier: License :: Other/Proprietary License
Classifier: Programming Language :: Python :: 3
Classifier: Programming Language :: Python :: 3.8
Classifier: Programming Language :: Python :: 3.9
Requires-Dist: lark (>=0.11.3,<0.12.0)
Requires-Dist: pendulum (>=2.1.2,<3.0.0)
